README.md
setup.py
rlbottraining/__init__.py
rlbottraining/__main__.py
rlbottraining/exercise_runner.py
rlbottraining/paths.py
rlbottraining/rng.py
rlbottraining/training_exercise.py
rlbottraining/training_exercise_adapter.py
rlbottraining/version.py
rlbottraining.egg-info/PKG-INFO
rlbottraining.egg-info/SOURCES.txt
rlbottraining.egg-info/dependency_links.txt
rlbottraining.egg-info/entry_points.txt
rlbottraining.egg-info/requires.txt
rlbottraining.egg-info/top_level.txt
rlbottraining/common_exercises/__init__.py
rlbottraining/common_exercises/ball_prediction.py
rlbottraining/common_exercises/bronze_goalie.py
rlbottraining/common_exercises/bronze_striker.py
rlbottraining/common_exercises/common_base_exercises.py
rlbottraining/common_exercises/dribbling.py
rlbottraining/common_exercises/human_versus_line_goalie.py
rlbottraining/common_exercises/kickoff_exercise.py
rlbottraining/common_exercises/silver_goalie.py
rlbottraining/common_exercises/silver_striker.py
rlbottraining/common_exercises/versus_line_goalie.py
rlbottraining/common_exercises/wall_play.py
rlbottraining/common_exercises/bakkesmod_import/__init__.py
rlbottraining/common_exercises/bakkesmod_import/bakkesmod_importer.py
rlbottraining/common_exercises/rl_custom_training_import/7657-2F43-9B3A-C1F1.json
rlbottraining/common_exercises/rl_custom_training_import/__init__.py
rlbottraining/common_exercises/rl_custom_training_import/rl_importer.py
rlbottraining/common_graders/__init__.py
rlbottraining/common_graders/ball_touches.py
rlbottraining/common_graders/compound_grader.py
rlbottraining/common_graders/goal_grader.py
rlbottraining/common_graders/kickoff_grader.py
rlbottraining/common_graders/rl_graders.py
rlbottraining/common_graders/tick_wrapper.py
rlbottraining/common_graders/timeout.py
rlbottraining/example_bots/__init__.py
rlbottraining/example_bots/brick_bot/__init__.py
rlbottraining/example_bots/brick_bot/brick_bot.cfg
rlbottraining/example_bots/brick_bot/brick_bot.py
rlbottraining/example_bots/brick_bot/brick_bot_looks.cfg
rlbottraining/example_bots/line_goalie/__init__.py
rlbottraining/example_bots/line_goalie/line_goalie.cfg
rlbottraining/example_bots/line_goalie/line_goalie.py
