Metadata-Version: 2.1
Name: rlbottraining
Version: 0.6.0
Summary: A framework for writing training for Rocket League bots.
Home-page: https://github.com/RLBot/RLBotTraining
Author: RLBot Community
Author-email: rlbotofficial@gmail.com
License: MIT License
Keywords: rocket-league,training,train
Platform: UNKNOWN
Classifier: Programming Language :: Python :: 3
Classifier: License :: OSI Approved :: MIT License
Classifier: Operating System :: Microsoft :: Windows
Requires-Python: >=3.7.0
